intsetwrap.py
procset.py
procset-1.0.dist-info/AUTHORS.rst
procset-1.0.dist-info/LICENSE.rst
procset-1.0.dist-info/METADATA
procset-1.0.dist-info/WHEEL
procset-1.0.dist-info/top_level.txt
procset-1.0.dist-info/RECORD
