Metadata-Version: 2.1
Name: procset
Version: 1.0
Summary: Toolkit to manage sets of closed intervals.
Home-page: https://gitlab.inria.fr/bleuse/procset.py
Author: Raphaël Bleuse
Author-email: cs@research.bleuse.net
License: LGPLv3
Project-URL: Documentation, https://procset.rtfd.io/en/stable/
Keywords: interval set,scheduling
Platform: UNKNOWN
Classifier: Development Status :: 5 - Production/Stable
Classifier: Intended Audience :: Developers
Classifier: Intended Audience :: Science/Research
Classifier: License :: OSI Approved :: GNU Lesser General Public License v3 (LGPLv3)
Classifier: Programming Language :: Python :: 3 :: Only
Classifier: Programming Language :: Python :: 3.5
Classifier: Programming Language :: Python :: 3.6
Classifier: Programming Language :: Python :: 3.7
Classifier: Topic :: Software Development :: Libraries :: Python Modules
Provides: interval_set
Obsoletes: interval_set
Provides-Extra: test
